collectington/__init__.py
collectington/abstract_api.py
collectington/ascii_art.py
collectington/collectington_api.py
collectington/config.py
collectington/logger.py
collectington/runner.py
collectington/utils.py
collectington/exceptions/__init__.py
collectington/exceptions/collection_exceptions.py
collectington/test/__init__.py
collectington/test/test_config.py
collectington/test/test_utils.py
collectington-0.1.4.data/scripts/cton
config/__init__.py
exceptions/__init__.py
exceptions/collection_exceptions.py
src/__init__.py
src/abstract_api.py
src/config.py
src/logger.py
src/runner.py
src/utils.py
test/__init__.py
test/test_config.py
test/test_utils.py
collectington-0.1.4.dist-info/LICENSE
collectington-0.1.4.dist-info/METADATA
collectington-0.1.4.dist-info/WHEEL
collectington-0.1.4.dist-info/top_level.txt
collectington-0.1.4.dist-info/RECORD
