Metadata-Version: 2.1
Name: collectington
Version: 0.1.4
Summary: Collectington is a framework that allows any 3rd party API data to be sent to Prometheus
Home-page: https://github.com/HomeXLabs/collectington
Author: YoungJun Park, Nathan Boswell, Eric Jalbert
Author-email: collectington@homex.com
License: MIT
Download-URL: https://github.com/HomeXLabs/collectington
Platform: UNKNOWN
Classifier: Programming Language :: Python :: 3
Classifier: License :: OSI Approved :: MIT License
Requires-Python: >=3.6
License-File: LICENSE
Requires-Dist: prometheus-client
Requires-Dist: termcolor
Requires-Dist: pyfiglet
Requires-Dist: requests
